extracthero/__init__.py
extracthero/ask_ai_to_analyze.py
extracthero/extracthero.py
extracthero/filter_engine.py
extracthero/filterhero.py
extracthero/myllmservice.py
extracthero/parse_engine.py
extracthero/parsehero.py
extracthero/prompts.py
extracthero/sample_dicts.py
extracthero/schemas.py
extracthero/show_html.py
extracthero/utils.py
extracthero-0.1.8.dist-info/METADATA
extracthero-0.1.8.dist-info/WHEEL
extracthero-0.1.8.dist-info/top_level.txt
extracthero-0.1.8.dist-info/RECORD
